rubberband.cpython-37m-darwin.so
rubberband-0.2.0.dist-info/LICENSE.rst
rubberband-0.2.0.dist-info/METADATA
rubberband-0.2.0.dist-info/WHEEL
rubberband-0.2.0.dist-info/top_level.txt
rubberband-0.2.0.dist-info/zip-safe
rubberband-0.2.0.dist-info/RECORD
